tbutils/__init__.py
tbutils/config.py
tbutils/exec_max_n.py
tbutils/info.py
tbutils/jax.py
tbutils/seed.py
tbutils/struct.py
tbutils/tmeasure.py
tbutils-1.1.dist-info/licenses/LICENSE
tbutils-1.1.dist-info/METADATA
tbutils-1.1.dist-info/WHEEL
tbutils-1.1.dist-info/top_level.txt
tbutils-1.1.dist-info/RECORD
