Metadata-Version: 2.4
Name: tbutils
Version: 1.1
Summary: tbutils is a package of utility functions for python.
Home-page: https://github.com/tboulet/tbutils
Author: Timothé Boulet
Author-email: timothe.boulet0@gmail.com
License: MIT
License-File: LICENSE
Dynamic: author
Dynamic: author-email
Dynamic: description
Dynamic: description-content-type
Dynamic: home-page
Dynamic: license
Dynamic: license-file
Dynamic: summary
